yazaki_packages/__init__.py
yazaki_packages/cloud.py
yazaki_packages/db.py
yazaki_packages/logs.py
yazaki_packages/yazaki.py
yazaki_packages-1.20210517.90949b0.dist-info/METADATA
yazaki_packages-1.20210517.90949b0.dist-info/WHEEL
yazaki_packages-1.20210517.90949b0.dist-info/top_level.txt
yazaki_packages-1.20210517.90949b0.dist-info/RECORD
