Metadata-Version: 2.1
Name: yazaki-packages
Version: 1.20210517.90949b0
Summary: Some description
Home-page: https://github.com/kanomthai/sync_cloud_xpw.git
Author: kanomthai
Author-email: krumii.it@gmail.com
License: MIT
Platform: UNKNOWN
Classifier: Programming Language :: Python :: 3
Classifier: License :: OSI Approved :: MIT License
Classifier: Development Status :: 3 - Alpha
Requires-Dist: requests
